{"type": "Feature", "id": 12523022, "geometry": {"type": "Point", "coordinates": [31.125, -16.7328]}, "properties": {"woe:id": 12523022, "woe:parent_id": 1466855, "woe:name": "Centenary Airport", "woe:placetype": 14, "woe:placetype_name": "Airport", "woe:lang": "ENG", "iso:country": "ZW", "meta:provider": ["geoplanet:7.3.1", "geoplanet:7.3.2", "geoplanet:7.4.0", "geoplanet:7.4.1", "geoplanet:7.5.1", "geoplanet:7.5.2", "geoplanet:7.6.0", "geoplanet:7.8.1", "geoplanet:7.9.0", "geoplanet:7.10.0", "geoplanet:8.0.0", "woeplanet:8.0.0"], "meta:indexed": "2020-08-20T20:57:43.313506", "meta:updated": "2020-10-14T10:59:56.733900", "woe:hierarchy": {"continent": 24865670, "country": 23425004, "town": 0, "planet": 1, "county": 56048487, "suburb": 0, "state": 2347812, "region": 0, "localadmin": 0}, "woe:timezone_id": 28350703, "woe:hash": "ktn0u3bs3h40", "woe:centroid": [31.125, -16.7328], "geom:latitude": -16.7328, "geom:longitude": 31.125, "geom:hash": "ktn0u3bs3h40", "woe:latitude": -16.7328, "geom:centroid": [31.125, -16.7328], "woe:longitude": 31.125, "woe:repo": "woeplanet-airport-zw", "geom:area": 0.0, "woe:scale": 19}}